devstat/__init__.py
devstat/devstat.py
devstat-0.0.1.dist-info/LICENSE
devstat-0.0.1.dist-info/METADATA
devstat-0.0.1.dist-info/WHEEL
devstat-0.0.1.dist-info/top_level.txt
devstat-0.0.1.dist-info/RECORD
