Metadata-Version: 2.1
Name: devstat
Version: 0.0.1
Summary: A system status library
Home-page: https://github.com/prashantdivate/devstat
Author: Prashant Divate
Author-email: diwateprashant44@gmail.com
License: UNKNOWN
Platform: UNKNOWN
Classifier: Programming Language :: Python :: 3
Classifier: License :: OSI Approved :: MIT License
Classifier: Operating System :: OS Independent
Requires-Python: >=3.6
